{
  "updated": "2026-07-12 02:08",
  "source": "CWA opendata (W-C0034-005 路徑潛勢)",
  "active": false,
  "tracking": true,
  "name": "巴威",
  "warning": "追蹤中，對雲林暫無直接威脅",
  "land_warning": false,
  "invade_prob": 0.0,
  "eta_iso": null,
  "eta_text": "追蹤中",
  "min_dist_km": 603,
  "rain_24h_mm": 550.0,
  "rain_1h_mm": 1.0,
  "rain": {
    "h1": 1.0,
    "h3": 1.5,
    "h6": 10.5,
    "h12": 132.5,
    "h24": 550.0,
    "d2": 553.5,
    "d3": 553.5
  },
  "forecast_gust_ms": null,
  "track": [
    {
      "t": "2026-07-12T05:00:00+08:00",
      "lat": 29.2,
      "lng": 120.1,
      "r15": 250,
      "r25": 0,
      "gust": 35.0
    },
    {
      "t": "2026-07-12T11:00:00+08:00",
      "lat": 30.6,
      "lng": 119.1,
      "r15": 200,
      "r25": 0,
      "gust": 33.0
    },
    {
      "t": "2026-07-12T17:00:00+08:00",
      "lat": 31.3,
      "lng": 118.2,
      "r15": 150,
      "r25": 0,
      "gust": 28.0
    },
    {
      "t": "2026-07-12T23:00:00+08:00",
      "lat": 31.9,
      "lng": 117.7,
      "r15": 120,
      "r25": 0,
      "gust": 25.0
    },
    {
      "t": "2026-07-13T11:00:00+08:00",
      "lat": 33.0,
      "lng": 117.4,
      "r15": 0,
      "r25": 0,
      "gust": 15.0
    }
  ]
}